kylinLLM/__init__.py
kylinLLM/classification.py
kylinLLM/cognition.py
kylinLLM/memory.py
kylinLLM/role.py
kylinLLM/strategy.py
kylinLLM-0.1.6.dist-info/METADATA
kylinLLM-0.1.6.dist-info/WHEEL
kylinLLM-0.1.6.dist-info/top_level.txt
kylinLLM-0.1.6.dist-info/RECORD
