Metadata-Version: 2.1
Name: kylinLLM
Version: 0.1.6
Summary: A package for large language model prompts
Author: QiMing
Author-email: 1316849135@qq.com
Classifier: Programming Language :: Python :: 3
Classifier: License :: OSI Approved :: MIT License
Classifier: Operating System :: OS Independent
